{
	"name": "pipeline2",
	"properties": {
		"activities": [
			{
				"name": "Web1",
				"type": "WebActivity",
				"dependsOn": [],
				"policy": {
					"timeout": "7.00:00:00",
					"retry": 0,
					"retryIntervalInSeconds": 30,
					"secureOutput": false,
					"secureInput": false
				},
				"userProperties": [],
				"typeProperties": {
					"url": "@concat('https://api.postalpincode.in/pincode/',pipeline().parameters.Pincode)",
					"method": "GET"
				}
			},
			{
				"name": "Stored procedure1",
				"type": "SqlServerStoredProcedure",
				"dependsOn": [
					{
						"activity": "Web1",
						"dependencyConditions": [
							"Succeeded"
						]
					}
				],
				"policy": {
					"timeout": "7.00:00:00",
					"retry": 0,
					"retryIntervalInSeconds": 30,
					"secureOutput": false,
					"secureInput": false
				},
				"userProperties": [],
				"typeProperties": {
					"storedProcedureName": "[dbo].[USP_Insert_Postal_Branch_D]",
					"storedProcedureParameters": {
						"block": {
							"value": {
								"value": "@json(activity('Web1').output.response)[0].PostOffice[0].Block",
								"type": "Expression"
							},
							"type": "String"
						},
						"Name": {
							"value": {
								"value": "@json(activity('Web1').output.response)[0].PostOffice[0].Name",
								"type": "Expression"
							},
							"type": "String"
						},
						"Description": {
							"value": {
								"value": "@json(activity('Web1').output.response)[0].PostOffice[0].Description",
								"type": "Expression"
							},
							"type": "String"
						},
						"BranchType": {
							"value": {
								"value": "@json(activity('Web1').output.response)[0].PostOffice[0].BranchType",
								"type": "Expression"
							},
							"type": "String"
						},
						"DeliveryStatus": {
							"value": {
								"value": "@json(activity('Web1').output.response)[0].PostOffice[0].DeliveryStatus",
								"type": "Expression"
							},
							"type": "String"
						},
						"Circle": {
							"value": {
								"value": "@json(activity('Web1').output.response)[0].PostOffice[0].Circle",
								"type": "Expression"
							},
							"type": "String"
						},
						"District": {
							"value": {
								"value": "@json(activity('Web1').output.response)[0].PostOffice[0].District",
								"type": "Expression"
							},
							"type": "String"
						},
						"Division": {
							"value": {
								"value": "@json(activity('Web1').output.response)[0].PostOffice[0].Division",
								"type": "Expression"
							},
							"type": "String"
						},
						"Region": {
							"value": {
								"value": "@json(activity('Web1').output.response)[0].PostOffice[0].Region",
								"type": "Expression"
							},
							"type": "String"
						},
						"State": {
							"value": {
								"value": "@json(activity('Web1').output.response)[0].PostOffice[0].State",
								"type": "Expression"
							},
							"type": "String"
						},
						"Country": {
							"value": {
								"value": "@json(activity('Web1').output.response)[0].PostOffice[0].Country",
								"type": "Expression"
							},
							"type": "String"
						},
						"Pincode": {
							"value": {
								"value": "@json(activity('Web1').output.response)[0].PostOffice[0].Pincode",
								"type": "Expression"
							},
							"type": "String"
						}
					}
				},
				"linkedServiceName": {
					"referenceName": "LS_src_business_db",
					"type": "LinkedServiceReference"
				}
			}
		],
		"parameters": {
			"Pincode": {
				"type": "string",
				"defaultValue": "500011"
			}
		},
		"annotations": []
	}
}